hichi/__init__.py
hichi/chat.py
hichi/cli.py
hichi/config.py
hichi/crypto.py
hichi-0.3.0.dist-info/licenses/LICENSE
hichi-0.3.0.dist-info/METADATA
hichi-0.3.0.dist-info/WHEEL
hichi-0.3.0.dist-info/entry_points.txt
hichi-0.3.0.dist-info/top_level.txt
hichi-0.3.0.dist-info/RECORD
