Metadata-Version: 2.4
Name: hichi
Version: 0.3.0
Summary: A CLI tool for interacting with Groq AI
Project-URL: Homepage, https://github.com/yourusername/hichi
Project-URL: Repository, https://github.com/yourusername/hichi
Requires-Python: >=3.8
License-File: LICENSE
Requires-Dist: click>=8.0.0
Requires-Dist: cryptography>=3.4.0
Requires-Dist: groq>=0.4.0
Provides-Extra: dev
Requires-Dist: pytest>=6.0; extra == "dev"
Requires-Dist: black>=21.0; extra == "dev"
Requires-Dist: flake8>=3.8; extra == "dev"
Dynamic: license-file
